ginacsympy.cp313-win_amd64.pyd
ginacsympy_abc.py
ginacsympy_version.py
ginacsympy-1.0.4.dist-info/licenses/LICENSE
ginacsympy-1.0.4.dist-info/METADATA
ginacsympy-1.0.4.dist-info/WHEEL
ginacsympy-1.0.4.dist-info/top_level.txt
ginacsympy-1.0.4.dist-info/RECORD
