Metadata-Version: 2.4
Name: ginacsympy
Version: 1.0.4
Summary: A Cython frontend to the fast C++ symbolic manipulation library GinacSym. 
Home-page: https://mithun218.github.io/ginacsympy/
Author: Mithun Bairagi
Author-email: bairagirasulpur@gmail.com
License: GPLv2 or above
Project-URL: Source, https://github.com/mithun218/ginacsympy
Platform: win32
Classifier: Programming Language :: Python :: 3
Classifier: Operating System :: OS Independent
Requires-Python: >=3.8
License-File: LICENSE
Dynamic: author
Dynamic: author-email
Dynamic: classifier
Dynamic: description
Dynamic: description-content-type
Dynamic: home-page
Dynamic: license
Dynamic: license-file
Dynamic: platform
Dynamic: project-url
Dynamic: requires-python
Dynamic: summary
